[{"title":"UK Drill 2022 Mix 🔥 Best UK Drill Songs 2022","url":"https://www.youtube.com/watch?v=3tK_KOyORIo","duration":"43:58"},{"title":"UK DRILL MIX 2021 #2 (FEATURING ARRDEE, TION WAYNE, CENTRAL CEE, RUSS MILLIONS, HEADIE ONE & MORE)","url":"https://www.youtube.com/watch?v=bhS1TqA9emE","duration":"18:09"},{"title":"UK Drill Music Playlist 🔥","url":"https://www.youtube.com/watch?v=jb_XZL0U8Dw","duration":"1:06:43"},{"title":"UK Drill 2022 Mix 🔥 Best UK Drill Songs 2022","url":"https://www.youtube.com/watch?v=c3TXVQVtkic","duration":"56:47"},{"title":"SR - Welcome To Brixton [Music Video] | GRM Daily","url":"https://www.youtube.com/watch?v=svxwIa5mxjQ","duration":"3:17"}]